{"card_name": "UA05 Meat Grinder", "color": "", "rarity": "uncommon", "type": "Artifact \u2013 Clue", "number": 251, "color_identity": "C", "cost": "{1}", "rules_text": "{T}, Sacrifice a creature: Put a +1/+1 counter on target creature. Create a Food token.\n{2}, Sacrifice this artifact: Draw a card.", "flavor_text": "[i]\u201cThe meaty dinners kept coming, and I began to wonder a bit about where he was getting it all.\u201d\n\u2014Statement of Mikaele Salesa[/i]", "pt": "", "special_text": "", "shape": "normal", "set": "TMA", "loyalty": "", "artist": "", "notes": "", "image_type": "png"}