{"card_name": "CW07 'Voltron Target'", "color": "W", "rarity": "common", "type": "Creature", "number": 8, "color_identity": "W", "cost": "{2}{W}", "rules_text": "Ward {2} [i](Whenever this creature becomes the target of a spell or ability an opponent controls, counter it unless that player pays {2}.)[/i]\n{3}{W}: Put a +1/+1 counter on this creature.", "flavor_text": "[i][/i]", "pt": "3/3", "special_text": "", "shape": "normal", "set": "FMA", "loyalty": "", "artist": "", "notes": "", "image_type": "png"}