{"card_name": "Twilight of Anor Londo", "color": "U", "rarity": "rare", "type": "Enchantment", "number": 80, "color_identity": "U", "cost": "{4}{U}{U}", "rules_text": "Each creature your opponents control is an Illusion in addition to its other types and has \u201cWhen this creature becomes the target of a spell or ability, sacrifice it.\u201d", "flavor_text": "[i]\u201cMark the words of mineself, Gwyndolin! Thou shalt not go unpunished.\u201d\n\u2014Dark Sun Gwyndolin[/i]", "pt": "", "special_text": "", "shape": "normal", "set": "LOR", "loyalty": "", "artist": "evs-eme", "notes": "", "image_type": "png"}